[
  {
    "ContainingType": "StockManagement.Controllers.BrandsController",
    "Method": "GetTestData",
    "RelativePath": "api/Brands",
    "HttpMethod": "GET",
    "IsController": true,
    "Order": 0,
    "Parameters": [],
    "ReturnTypes": []
  },
  {
    "ContainingType": "StockManagement.Controllers.BrandsController",
    "Method": "PostItem",
    "RelativePath": "api/Brands",
    "HttpMethod": "POST",
    "IsController": true,
    "Order": 0,
    "Parameters": [
      {
        "Name": "Brand",
        "Type": "StockManagement.Models.Brand",
        "IsRequired": true
      }
    ],
    "ReturnTypes": []
  },
  {
    "ContainingType": "StockManagement.Controllers.CategoriesController",
    "Method": "GetTestData",
    "RelativePath": "api/Categories",
    "HttpMethod": "GET",
    "IsController": true,
    "Order": 0,
    "Parameters": [],
    "ReturnTypes": []
  },
  {
    "ContainingType": "StockManagement.Controllers.ItemsController",
    "Method": "GetItems",
    "RelativePath": "api/Items",
    "HttpMethod": "GET",
    "IsController": true,
    "Order": 0,
    "Parameters": [],
    "ReturnTypes": [
      {
        "Type": "System.Collections.Generic.IEnumerable\u00601[[StockManagement.Models.Item, StockManagement, Version=1.0.0.0, Culture=neutral, PublicKeyToken=null]]",
        "MediaTypes": [
          "text/plain",
          "application/json",
          "text/json"
        ],
        "StatusCode": 200
      }
    ]
  },
  {
    "ContainingType": "StockManagement.Controllers.ItemsController",
    "Method": "PostItem",
    "RelativePath": "api/Items",
    "HttpMethod": "POST",
    "IsController": true,
    "Order": 0,
    "Parameters": [
      {
        "Name": "item",
        "Type": "StockManagement.Models.Item",
        "IsRequired": true
      }
    ],
    "ReturnTypes": []
  },
  {
    "ContainingType": "StockManagement.Controllers.ItemsController",
    "Method": "AddItemsBulk",
    "RelativePath": "api/Items/bulk",
    "HttpMethod": "POST",
    "IsController": true,
    "Order": 0,
    "Parameters": [
      {
        "Name": "items",
        "Type": "System.Collections.Generic.List\u00601[[StockManagement.Models.Item, StockManagement, Version=1.0.0.0, Culture=neutral, PublicKeyToken=null]]",
        "IsRequired": true
      }
    ],
    "ReturnTypes": []
  }
]